hydrodataset/__init__.py
hydrodataset/_version.py
hydrodataset/arcade.py
hydrodataset/bull.py
hydrodataset/camels.py
hydrodataset/camels_aus.py
hydrodataset/camels_br.py
hydrodataset/camels_ch.py
hydrodataset/camels_cl.py
hydrodataset/camels_col.py
hydrodataset/camels_de.py
hydrodataset/camels_deby.py
hydrodataset/camels_dk.py
hydrodataset/camels_es.py
hydrodataset/camels_fi.py
hydrodataset/camels_fr.py
hydrodataset/camels_gb.py
hydrodataset/camels_ind.py
hydrodataset/camels_lux.py
hydrodataset/camels_nz.py
hydrodataset/camels_se.py
hydrodataset/camels_us.py
hydrodataset/camelsh.py
hydrodataset/camelsh_kr.py
hydrodataset/caravan.py
hydrodataset/caravan_dk.py
hydrodataset/estreams.py
hydrodataset/grdc_caravan.py
hydrodataset/hds_utils.py
hydrodataset/hyd_responses.py
hydrodataset/hydro_dataset.py
hydrodataset/hype.py
hydrodataset/hysets.py
hydrodataset/ireland.py
hydrodataset/italy.py
hydrodataset/jialingriverchina.py
hydrodataset/lamah_ce.py
hydrodataset/lamah_ice.py
hydrodataset/mopex.py
hydrodataset/multi_datasets.py
hydrodataset/poland.py
hydrodataset/portugal.py
hydrodataset/simbi.py
hydrodataset/slovenia.py
hydrodataset/waterbenchiowa.py
hydrodataset-0.2.4.dist-info/METADATA
hydrodataset-0.2.4.dist-info/WHEEL
hydrodataset-0.2.4.dist-info/licenses/AUTHORS.rst
hydrodataset-0.2.4.dist-info/licenses/LICENSE
hydrodataset-0.2.4.dist-info/RECORD
