Metadata-Version: 2.4
Name: hydrodataset
Version: 0.2.4
Summary: A Python package for downloading and reading hydrological datasets
Project-URL: Homepage, https://github.com/OuyangWenyu/hydrodataset
Project-URL: Repository, https://github.com/OuyangWenyu/hydrodataset
Project-URL: Documentation, https://github.com/OuyangWenyu/hydrodataset
Project-URL: Bug Tracker, https://github.com/OuyangWenyu/hydrodataset/issues
Author-email: Wenyu Ouyang <wenyuouyang@outlook.com>
Maintainer-email: Wenyu Ouyang <wenyuouyang@outlook.com>
License: MIT
License-File: AUTHORS.rst
License-File: LICENSE
Keywords: datasets,hydrodataset,hydrology,water
Classifier: Development Status :: 2 - Pre-Alpha
Classifier: Intended Audience :: Developers
Classifier: License :: OSI Approved :: MIT License
Classifier: Natural Language :: English
Classifier: Programming Language :: Python :: 3
Classifier: Programming Language :: Python :: 3.10
Classifier: Programming Language :: Python :: 3.11
Classifier: Programming Language :: Python :: 3.12
Requires-Python: >=3.10
Requires-Dist: aqua-fetch[all]
Requires-Dist: bokeh>=2.4.2
Requires-Dist: codetiming
Requires-Dist: dask[complete]
Requires-Dist: dask[distributed]
Requires-Dist: hydroutils
Requires-Dist: netcdf4
Requires-Dist: openpyxl>=3.1.5
Requires-Dist: pint
Requires-Dist: pint-pandas
Requires-Dist: pint-xarray
Requires-Dist: py7zr>=1.0.0
Requires-Dist: requests>=2.32.4
Requires-Dist: scipy
Requires-Dist: tzfpy
Requires-Dist: xarray
Requires-Dist: xlrd>=2.0.2
Requires-Dist: zarr
Provides-Extra: dev
Requires-Dist: black; extra == 'dev'
Requires-Dist: bump2version; extra == 'dev'
Requires-Dist: coverage; extra == 'dev'
Requires-Dist: flake8; extra == 'dev'
Requires-Dist: grip; extra == 'dev'
Requires-Dist: pytest-runner; extra == 'dev'
Requires-Dist: pytest>=3; extra == 'dev'
Requires-Dist: sphinx; extra == 'dev'
Requires-Dist: tox; extra == 'dev'
Requires-Dist: twine; extra == 'dev'
Requires-Dist: watchdog; extra == 'dev'
Requires-Dist: wheel; extra == 'dev'
Provides-Extra: docs
Requires-Dist: grip; extra == 'docs'
Requires-Dist: ipykernel; extra == 'docs'
Requires-Dist: mkdocs-git-revision-date-plugin; extra == 'docs'
Requires-Dist: mkdocs-jupyter; extra == 'docs'
Requires-Dist: mkdocs-material; extra == 'docs'
Requires-Dist: mkdocstrings; extra == 'docs'
Requires-Dist: mkdocstrings-python; extra == 'docs'
Requires-Dist: sphinx; extra == 'docs'
Provides-Extra: lint
Requires-Dist: black; extra == 'lint'
Requires-Dist: flake8; extra == 'lint'
Provides-Extra: release
Requires-Dist: build; extra == 'release'
Requires-Dist: hatch-vcs; extra == 'release'
Requires-Dist: hatchling; extra == 'release'
Requires-Dist: twine; extra == 'release'
